kipoiseq/__init__.py
kipoiseq/dataclasses.py
kipoiseq/utils.py
kipoiseq/variant_source.py
kipoiseq/dataloaders/__init__.py
kipoiseq/dataloaders/protein.py
kipoiseq/dataloaders/sequence.py
kipoiseq/dataloaders/splicing.py
kipoiseq/extractors/__init__.py
kipoiseq/extractors/base.py
kipoiseq/extractors/fasta.py
kipoiseq/extractors/gtf.py
kipoiseq/extractors/multi_interval.py
kipoiseq/extractors/protein.py
kipoiseq/extractors/vcf.py
kipoiseq/extractors/vcf_matching.py
kipoiseq/extractors/vcf_query.py
kipoiseq/extractors/vcf_seq.py
kipoiseq/transforms/__init__.py
kipoiseq/transforms/functional.py
kipoiseq/transforms/transforms.py
kipoiseq-0.7.1.dist-info/LICENSE
kipoiseq-0.7.1.dist-info/METADATA
kipoiseq-0.7.1.dist-info/WHEEL
kipoiseq-0.7.1.dist-info/top_level.txt
kipoiseq-0.7.1.dist-info/RECORD
