Metadata-Version: 2.1
Name: kipoiseq
Version: 0.7.1
Summary: kipoiseq: sequence-based data-loaders for Kipoi
Home-page: https://github.com/kipoi/kipoiseq
Author: Kipoi team
Author-email: avsec@in.tum.de
License: MIT license
Keywords: model zoo,deep learning,computational biology,bioinformatics,genomics
Platform: UNKNOWN
Requires-Python: >=3.6
License-File: LICENSE
Requires-Dist: kipoi (>=0.5.5)
Requires-Dist: pyfaidx
Requires-Dist: numpy
Requires-Dist: pandas
Requires-Dist: tqdm
Requires-Dist: gffutils
Requires-Dist: kipoi-utils (>=0.1.1)
Requires-Dist: kipoi-conda (>=0.1.0)
Requires-Dist: pyranges
Provides-Extra: develop
Requires-Dist: bumpversion ; extra == 'develop'
Requires-Dist: wheel ; extra == 'develop'
Requires-Dist: epc ; extra == 'develop'
Requires-Dist: jedi ; extra == 'develop'
Requires-Dist: pytest (>=3.3.1) ; extra == 'develop'
Requires-Dist: pytest-xdist ; extra == 'develop'
Requires-Dist: pytest-pep8 ; extra == 'develop'
Requires-Dist: pytest-mock ; extra == 'develop'
Requires-Dist: pytest-cov ; extra == 'develop'
Requires-Dist: coveralls ; extra == 'develop'
Requires-Dist: scikit-learn ; extra == 'develop'
Requires-Dist: cython ; extra == 'develop'
Requires-Dist: cyvcf2 ; extra == 'develop'
Requires-Dist: pyranges (>=0.0.71) ; extra == 'develop'
Requires-Dist: pybedtools ; extra == 'develop'
